pyros/__init__.py
pyroslib/__init__.py
pyroslib/logging.py
pyroslib/pyroslib.py
pyros_client-1.0.1.dist-info/LICENSE
pyros_client-1.0.1.dist-info/METADATA
pyros_client-1.0.1.dist-info/WHEEL
pyros_client-1.0.1.dist-info/top_level.txt
pyros_client-1.0.1.dist-info/RECORD
