Metadata-Version: 2.1
Name: pyros-client
Version: 1.0.1
Summary: Support library for PyROS
Home-page: https://github.com/Abstract-Horizon/pyros-client
Author: Daniel Sendula
License: UNKNOWN
Platform: UNKNOWN
Classifier: Programming Language :: Python :: 3
Classifier: License :: OSI Approved :: Apache Software License
Classifier: Operating System :: OS Independent
Requires-Python: >=3.6
License-File: LICENSE
Requires-Dist: paho-mqtt
